<?xml version="1.0" encoding="UTF-8"?>
<!DOCTYPE calibration SYSTEM "ftu_rx_cal.dtd">
<!-- Auto sgenerated XML file All pertinent data is represented as 
	XML elements XML attributes are reserved for Metadata ("data about the data") -->
<FTUCalibrationRx version="1" country="UK" facility="Swindon"
	operator="Jason">
	<!-- The Radio HW could support a multitude of platforms e.g. RRH, DIR, 
		PIM, FTU as identified by id -->
	<RxOpenLoop comment="Calibration for Signal Analysis">
		<!-- The individual Path calibrations are here so as to support different 
			methods, temperature compensations etc. -->
		<Path>1</Path>
		<Date>10/01/2008 15:12:33</Date>
		<LinearTemperatureCompensation>
			<!-- support for multiple methods i.e. linear, ploy, LUT. These are normally 
				fixed at design time against hardware revision from engineers logbook -->
			<Coefficient units="dB/DegC">0.05</Coefficient>
		</LinearTemperatureCompensation>
		<FrequencyBand
			comment="A frequency band represents a small section of the spectrum i.e. a cellular band which share a common IFDSA cal Point
				Frequencies are in kHz, IF and RF DSAs are in dB.">
			<Upper>2400000</Upper>
			<Lower>2300000</Lower>
			<IFDSA>5.5</IFDSA>
			<FrequencyTable>
				<Frequency>2325000</Frequency>
				<Temperature>23.5</Temperature>
				<Point>
					<RFDSA>0.0</RFDSA>
					<dBFS2dBm>-12.19</dBFS2dBm>
				</Point>
				<Point>
					<RFDSA>1.0</RFDSA>
					<dBFS2dBm>-12.19</dBFS2dBm>
				</Point>
				<Point>
					<RFDSA>2.0</RFDSA>
					<dBFS2dBm>-12.19</dBFS2dBm>
				</Point>
				<Point>
					<RFDSA>3.0</RFDSA>
					<dBFS2dBm>-12.19</dBFS2dBm>
				</Point>
				<Point>
					<RFDSA>4.0</RFDSA>
					<dBFS2dBm>-11.19</dBFS2dBm>
				</Point>
				<Point>
					<RFDSA>5.0</RFDSA>
					<dBFS2dBm>-10.19</dBFS2dBm>
				</Point>
				<Point>
					<RFDSA>6.0</RFDSA>
					<dBFS2dBm>-9.19</dBFS2dBm>
				</Point>
				<Point>
					<RFDSA>7.0</RFDSA>
					<dBFS2dBm>-8.19</dBFS2dBm>
				</Point>
				<Point>
					<RFDSA>8.0</RFDSA>
					<dBFS2dBm>-7.19</dBFS2dBm>
				</Point>
				<Point>
					<RFDSA>9.0</RFDSA>
					<dBFS2dBm>-6.19</dBFS2dBm>
				</Point>
				<Point>
					<RFDSA>10.0</RFDSA>
					<dBFS2dBm>-5.19</dBFS2dBm>
				</Point>
				<Point>
					<RFDSA>11.0</RFDSA>
					<dBFS2dBm>-4.19</dBFS2dBm>
				</Point>
				<Point>
					<RFDSA>12.0</RFDSA>
					<dBFS2dBm>-3.19</dBFS2dBm>
				</Point>
				<Point>
					<RFDSA>13.0</RFDSA>
					<dBFS2dBm>-2.19</dBFS2dBm>
				</Point>
				<Point>
					<RFDSA>14.0</RFDSA>
					<dBFS2dBm>-1.19</dBFS2dBm>
				</Point>
				<Point>
					<RFDSA>15.0</RFDSA>
					<dBFS2dBm>0.19</dBFS2dBm>
				</Point>
				<Point>
					<RFDSA>16.0</RFDSA>
					<dBFS2dBm>1.19</dBFS2dBm>
				</Point>
				<Point>
					<RFDSA>17.0</RFDSA>
					<dBFS2dBm>2.19</dBFS2dBm>
				</Point>
				<Point>
					<RFDSA>18.0</RFDSA>
					<dBFS2dBm>3.19</dBFS2dBm>
				</Point>
				<Point>
					<RFDSA>19.0</RFDSA>
					<dBFS2dBm>4.19</dBFS2dBm>
				</Point>
				<Point>
					<RFDSA>20.0</RFDSA>
					<dBFS2dBm>5.19</dBFS2dBm>
				</Point>
				<Point>
					<RFDSA>21.0</RFDSA>
					<dBFS2dBm>6.19</dBFS2dBm>
				</Point>
				<Point>
					<RFDSA>22.0</RFDSA>
					<dBFS2dBm>7.19</dBFS2dBm>
				</Point>
				<Point>
					<RFDSA>23.0</RFDSA>
					<dBFS2dBm>8.19</dBFS2dBm>
				</Point>
				<Point>
					<RFDSA>24.0</RFDSA>
					<dBFS2dBm>9.19</dBFS2dBm>
				</Point>
				<Point>
					<RFDSA>25.0</RFDSA>
					<dBFS2dBm>10.19</dBFS2dBm>
				</Point>
				<Point>
					<RFDSA>26.0</RFDSA>
					<dBFS2dBm>11.19</dBFS2dBm>
				</Point>
				<Point>
					<RFDSA>27.0</RFDSA>
					<dBFS2dBm>12.19</dBFS2dBm>
				</Point>
				<Point>
					<RFDSA>28.0</RFDSA>
					<dBFS2dBm>13.19</dBFS2dBm>
				</Point>
				<Point>
					<RFDSA>29.0</RFDSA>
					<dBFS2dBm>14.19</dBFS2dBm>
				</Point>
				<Point>
					<RFDSA>30.0</RFDSA>
					<dBFS2dBm>15.19</dBFS2dBm>
				</Point>
				<Point>
					<RFDSA>31.0</RFDSA>
					<dBFS2dBm>16.19</dBFS2dBm>
				</Point>
			</FrequencyTable>
			<FrequencyTable>
				<Frequency>2335000</Frequency>
				<Temperature>23.5</Temperature>
				<Point>
					<RFDSA>0.0</RFDSA>
					<dBFS2dBm>-12.29</dBFS2dBm>
				</Point>
				<Point>
					<RFDSA>1.0</RFDSA>
					<dBFS2dBm>-12.29</dBFS2dBm>
				</Point>
				<Point>
					<RFDSA>2.0</RFDSA>
					<dBFS2dBm>-12.29</dBFS2dBm>
				</Point>
				<Point>
					<RFDSA>3.0</RFDSA>
					<dBFS2dBm>-12.29</dBFS2dBm>
				</Point>
				<Point>
					<RFDSA>4.0</RFDSA>
					<dBFS2dBm>-11.29</dBFS2dBm>
				</Point>
				<Point>
					<RFDSA>5.0</RFDSA>
					<dBFS2dBm>-10.29</dBFS2dBm>
				</Point>
				<Point>
					<RFDSA>6.0</RFDSA>
					<dBFS2dBm>-9.29</dBFS2dBm>
				</Point>
				<Point>
					<RFDSA>7.0</RFDSA>
					<dBFS2dBm>-8.29</dBFS2dBm>
				</Point>
				<Point>
					<RFDSA>8.0</RFDSA>
					<dBFS2dBm>-7.29</dBFS2dBm>
				</Point>
				<Point>
					<RFDSA>9.0</RFDSA>
					<dBFS2dBm>-6.29</dBFS2dBm>
				</Point>
				<Point>
					<RFDSA>10.0</RFDSA>
					<dBFS2dBm>-5.29</dBFS2dBm>
				</Point>
				<Point>
					<RFDSA>11.0</RFDSA>
					<dBFS2dBm>-4.29</dBFS2dBm>
				</Point>
				<Point>
					<RFDSA>12.0</RFDSA>
					<dBFS2dBm>-3.29</dBFS2dBm>
				</Point>
				<Point>
					<RFDSA>13.0</RFDSA>
					<dBFS2dBm>-2.29</dBFS2dBm>
				</Point>
				<Point>
					<RFDSA>14.0</RFDSA>
					<dBFS2dBm>-1.29</dBFS2dBm>
				</Point>
				<Point>
					<RFDSA>15.0</RFDSA>
					<dBFS2dBm>0.29</dBFS2dBm>
				</Point>
				<Point>
					<RFDSA>16.0</RFDSA>
					<dBFS2dBm>1.29</dBFS2dBm>
				</Point>
				<Point>
					<RFDSA>17.0</RFDSA>
					<dBFS2dBm>2.29</dBFS2dBm>
				</Point>
				<Point>
					<RFDSA>18.0</RFDSA>
					<dBFS2dBm>3.29</dBFS2dBm>
				</Point>
				<Point>
					<RFDSA>19.0</RFDSA>
					<dBFS2dBm>4.29</dBFS2dBm>
				</Point>
				<Point>
					<RFDSA>20.0</RFDSA>
					<dBFS2dBm>5.29</dBFS2dBm>
				</Point>
				<Point>
					<RFDSA>21.0</RFDSA>
					<dBFS2dBm>6.29</dBFS2dBm>
				</Point>
				<Point>
					<RFDSA>22.0</RFDSA>
					<dBFS2dBm>7.29</dBFS2dBm>
				</Point>
				<Point>
					<RFDSA>23.0</RFDSA>
					<dBFS2dBm>8.29</dBFS2dBm>
				</Point>
				<Point>
					<RFDSA>24.0</RFDSA>
					<dBFS2dBm>9.29</dBFS2dBm>
				</Point>
				<Point>
					<RFDSA>25.0</RFDSA>
					<dBFS2dBm>10.29</dBFS2dBm>
				</Point>
				<Point>
					<RFDSA>26.0</RFDSA>
					<dBFS2dBm>11.29</dBFS2dBm>
				</Point>
				<Point>
					<RFDSA>27.0</RFDSA>
					<dBFS2dBm>12.29</dBFS2dBm>
				</Point>
				<Point>
					<RFDSA>28.0</RFDSA>
					<dBFS2dBm>13.29</dBFS2dBm>
				</Point>
				<Point>
					<RFDSA>29.0</RFDSA>
					<dBFS2dBm>14.29</dBFS2dBm>
				</Point>
				<Point>
					<RFDSA>30.0</RFDSA>
					<dBFS2dBm>15.29</dBFS2dBm>
				</Point>
				<Point>
					<RFDSA>31.0</RFDSA>
					<dBFS2dBm>16.29</dBFS2dBm>
				</Point>
			</FrequencyTable>
			<FrequencyTable>
				<Frequency>2345000</Frequency>
				<Temperature>23.5</Temperature>
				<Point>
					<RFDSA>0.0</RFDSA>
					<dBFS2dBm>-12.39</dBFS2dBm>
				</Point>
				<Point>
					<RFDSA>1.0</RFDSA>
					<dBFS2dBm>-12.39</dBFS2dBm>
				</Point>
				<Point>
					<RFDSA>2.0</RFDSA>
					<dBFS2dBm>-12.39</dBFS2dBm>
				</Point>
				<Point>
					<RFDSA>3.0</RFDSA>
					<dBFS2dBm>-12.39</dBFS2dBm>
				</Point>
				<Point>
					<RFDSA>4.0</RFDSA>
					<dBFS2dBm>-11.39</dBFS2dBm>
				</Point>
				<Point>
					<RFDSA>5.0</RFDSA>
					<dBFS2dBm>-10.39</dBFS2dBm>
				</Point>
				<Point>
					<RFDSA>6.0</RFDSA>
					<dBFS2dBm>-9.39</dBFS2dBm>
				</Point>
				<Point>
					<RFDSA>7.0</RFDSA>
					<dBFS2dBm>-8.39</dBFS2dBm>
				</Point>
				<Point>
					<RFDSA>8.0</RFDSA>
					<dBFS2dBm>-7.39</dBFS2dBm>
				</Point>
				<Point>
					<RFDSA>9.0</RFDSA>
					<dBFS2dBm>-6.39</dBFS2dBm>
				</Point>
				<Point>
					<RFDSA>10.0</RFDSA>
					<dBFS2dBm>-5.39</dBFS2dBm>
				</Point>
				<Point>
					<RFDSA>11.0</RFDSA>
					<dBFS2dBm>-4.39</dBFS2dBm>
				</Point>
				<Point>
					<RFDSA>12.0</RFDSA>
					<dBFS2dBm>-3.39</dBFS2dBm>
				</Point>
				<Point>
					<RFDSA>13.0</RFDSA>
					<dBFS2dBm>-2.39</dBFS2dBm>
				</Point>
				<Point>
					<RFDSA>14.0</RFDSA>
					<dBFS2dBm>-1.39</dBFS2dBm>
				</Point>
				<Point>
					<RFDSA>15.0</RFDSA>
					<dBFS2dBm>0.39</dBFS2dBm>
				</Point>
				<Point>
					<RFDSA>16.0</RFDSA>
					<dBFS2dBm>1.39</dBFS2dBm>
				</Point>
				<Point>
					<RFDSA>17.0</RFDSA>
					<dBFS2dBm>2.39</dBFS2dBm>
				</Point>
				<Point>
					<RFDSA>18.0</RFDSA>
					<dBFS2dBm>3.39</dBFS2dBm>
				</Point>
				<Point>
					<RFDSA>19.0</RFDSA>
					<dBFS2dBm>4.39</dBFS2dBm>
				</Point>
				<Point>
					<RFDSA>20.0</RFDSA>
					<dBFS2dBm>5.39</dBFS2dBm>
				</Point>
				<Point>
					<RFDSA>21.0</RFDSA>
					<dBFS2dBm>6.39</dBFS2dBm>
				</Point>
				<Point>
					<RFDSA>22.0</RFDSA>
					<dBFS2dBm>7.39</dBFS2dBm>
				</Point>
				<Point>
					<RFDSA>23.0</RFDSA>
					<dBFS2dBm>8.39</dBFS2dBm>
				</Point>
				<Point>
					<RFDSA>24.0</RFDSA>
					<dBFS2dBm>9.39</dBFS2dBm>
				</Point>
				<Point>
					<RFDSA>25.0</RFDSA>
					<dBFS2dBm>10.39</dBFS2dBm>
				</Point>
				<Point>
					<RFDSA>26.0</RFDSA>
					<dBFS2dBm>11.39</dBFS2dBm>
				</Point>
				<Point>
					<RFDSA>27.0</RFDSA>
					<dBFS2dBm>12.39</dBFS2dBm>
				</Point>
				<Point>
					<RFDSA>28.0</RFDSA>
					<dBFS2dBm>13.39</dBFS2dBm>
				</Point>
				<Point>
					<RFDSA>29.0</RFDSA>
					<dBFS2dBm>14.39</dBFS2dBm>
				</Point>
				<Point>
					<RFDSA>30.0</RFDSA>
					<dBFS2dBm>15.39</dBFS2dBm>
				</Point>
				<Point>
					<RFDSA>31.0</RFDSA>
					<dBFS2dBm>16.39</dBFS2dBm>
				</Point>
			</FrequencyTable>
			<FrequencyTable>
				<Frequency>2355000</Frequency>
				<Temperature>23.5</Temperature>
				<Point>
					<RFDSA>0.0</RFDSA>
					<dBFS2dBm>-12.49</dBFS2dBm>
				</Point>
				<Point>
					<RFDSA>1.0</RFDSA>
					<dBFS2dBm>-12.49</dBFS2dBm>
				</Point>
				<Point>
					<RFDSA>2.0</RFDSA>
					<dBFS2dBm>-12.49</dBFS2dBm>
				</Point>
				<Point>
					<RFDSA>3.0</RFDSA>
					<dBFS2dBm>-12.49</dBFS2dBm>
				</Point>
				<Point>
					<RFDSA>4.0</RFDSA>
					<dBFS2dBm>-11.49</dBFS2dBm>
				</Point>
				<Point>
					<RFDSA>5.0</RFDSA>
					<dBFS2dBm>-10.49</dBFS2dBm>
				</Point>
				<Point>
					<RFDSA>6.0</RFDSA>
					<dBFS2dBm>-9.49</dBFS2dBm>
				</Point>
				<Point>
					<RFDSA>7.0</RFDSA>
					<dBFS2dBm>-8.49</dBFS2dBm>
				</Point>
				<Point>
					<RFDSA>8.0</RFDSA>
					<dBFS2dBm>-7.49</dBFS2dBm>
				</Point>
				<Point>
					<RFDSA>9.0</RFDSA>
					<dBFS2dBm>-6.49</dBFS2dBm>
				</Point>
				<Point>
					<RFDSA>10.0</RFDSA>
					<dBFS2dBm>-5.49</dBFS2dBm>
				</Point>
				<Point>
					<RFDSA>11.0</RFDSA>
					<dBFS2dBm>-4.49</dBFS2dBm>
				</Point>
				<Point>
					<RFDSA>12.0</RFDSA>
					<dBFS2dBm>-3.49</dBFS2dBm>
				</Point>
				<Point>
					<RFDSA>13.0</RFDSA>
					<dBFS2dBm>-2.49</dBFS2dBm>
				</Point>
				<Point>
					<RFDSA>14.0</RFDSA>
					<dBFS2dBm>-1.49</dBFS2dBm>
				</Point>
				<Point>
					<RFDSA>15.0</RFDSA>
					<dBFS2dBm>0.49</dBFS2dBm>
				</Point>
				<Point>
					<RFDSA>16.0</RFDSA>
					<dBFS2dBm>1.49</dBFS2dBm>
				</Point>
				<Point>
					<RFDSA>17.0</RFDSA>
					<dBFS2dBm>2.49</dBFS2dBm>
				</Point>
				<Point>
					<RFDSA>18.0</RFDSA>
					<dBFS2dBm>3.49</dBFS2dBm>
				</Point>
				<Point>
					<RFDSA>19.0</RFDSA>
					<dBFS2dBm>4.49</dBFS2dBm>
				</Point>
				<Point>
					<RFDSA>20.0</RFDSA>
					<dBFS2dBm>5.49</dBFS2dBm>
				</Point>
				<Point>
					<RFDSA>21.0</RFDSA>
					<dBFS2dBm>6.49</dBFS2dBm>
				</Point>
				<Point>
					<RFDSA>22.0</RFDSA>
					<dBFS2dBm>7.49</dBFS2dBm>
				</Point>
				<Point>
					<RFDSA>23.0</RFDSA>
					<dBFS2dBm>8.49</dBFS2dBm>
				</Point>
				<Point>
					<RFDSA>24.0</RFDSA>
					<dBFS2dBm>9.49</dBFS2dBm>
				</Point>
				<Point>
					<RFDSA>25.0</RFDSA>
					<dBFS2dBm>10.49</dBFS2dBm>
				</Point>
				<Point>
					<RFDSA>26.0</RFDSA>
					<dBFS2dBm>11.49</dBFS2dBm>
				</Point>
				<Point>
					<RFDSA>27.0</RFDSA>
					<dBFS2dBm>12.49</dBFS2dBm>
				</Point>
				<Point>
					<RFDSA>28.0</RFDSA>
					<dBFS2dBm>13.49</dBFS2dBm>
				</Point>
				<Point>
					<RFDSA>29.0</RFDSA>
					<dBFS2dBm>14.49</dBFS2dBm>
				</Point>
				<Point>
					<RFDSA>30.0</RFDSA>
					<dBFS2dBm>15.49</dBFS2dBm>
				</Point>
				<Point>
					<RFDSA>31.0</RFDSA>
					<dBFS2dBm>16.49</dBFS2dBm>
				</Point>
			</FrequencyTable>
			<FrequencyTable>
				<Frequency>2365000</Frequency>
				<Temperature>25.0</Temperature>
				<Point>
					<RFDSA>0.0</RFDSA>
					<dBFS2dBm>-12.59</dBFS2dBm>
				</Point>
				<Point>
					<RFDSA>1.0</RFDSA>
					<dBFS2dBm>-12.59</dBFS2dBm>
				</Point>
				<Point>
					<RFDSA>2.0</RFDSA>
					<dBFS2dBm>-12.59</dBFS2dBm>
				</Point>
				<Point>
					<RFDSA>3.0</RFDSA>
					<dBFS2dBm>-12.59</dBFS2dBm>
				</Point>
				<Point>
					<RFDSA>4.0</RFDSA>
					<dBFS2dBm>-11.59</dBFS2dBm>
				</Point>
				<Point>
					<RFDSA>5.0</RFDSA>
					<dBFS2dBm>-10.59</dBFS2dBm>
				</Point>
				<Point>
					<RFDSA>6.0</RFDSA>
					<dBFS2dBm>-9.59</dBFS2dBm>
				</Point>
				<Point>
					<RFDSA>7.0</RFDSA>
					<dBFS2dBm>-8.59</dBFS2dBm>
				</Point>
				<Point>
					<RFDSA>8.0</RFDSA>
					<dBFS2dBm>-7.59</dBFS2dBm>
				</Point>
				<Point>
					<RFDSA>9.0</RFDSA>
					<dBFS2dBm>-6.59</dBFS2dBm>
				</Point>
				<Point>
					<RFDSA>10.0</RFDSA>
					<dBFS2dBm>-5.59</dBFS2dBm>
				</Point>
				<Point>
					<RFDSA>11.0</RFDSA>
					<dBFS2dBm>-4.59</dBFS2dBm>
				</Point>
				<Point>
					<RFDSA>12.0</RFDSA>
					<dBFS2dBm>-3.59</dBFS2dBm>
				</Point>
				<Point>
					<RFDSA>13.0</RFDSA>
					<dBFS2dBm>-2.59</dBFS2dBm>
				</Point>
				<Point>
					<RFDSA>14.0</RFDSA>
					<dBFS2dBm>-1.59</dBFS2dBm>
				</Point>
				<Point>
					<RFDSA>15.0</RFDSA>
					<dBFS2dBm>0.59</dBFS2dBm>
				</Point>
				<Point>
					<RFDSA>16.0</RFDSA>
					<dBFS2dBm>1.59</dBFS2dBm>
				</Point>
				<Point>
					<RFDSA>17.0</RFDSA>
					<dBFS2dBm>2.59</dBFS2dBm>
				</Point>
				<Point>
					<RFDSA>18.0</RFDSA>
					<dBFS2dBm>3.59</dBFS2dBm>
				</Point>
				<Point>
					<RFDSA>19.0</RFDSA>
					<dBFS2dBm>4.59</dBFS2dBm>
				</Point>
				<Point>
					<RFDSA>20.0</RFDSA>
					<dBFS2dBm>5.59</dBFS2dBm>
				</Point>
				<Point>
					<RFDSA>21.0</RFDSA>
					<dBFS2dBm>6.59</dBFS2dBm>
				</Point>
				<Point>
					<RFDSA>22.0</RFDSA>
					<dBFS2dBm>7.59</dBFS2dBm>
				</Point>
				<Point>
					<RFDSA>23.0</RFDSA>
					<dBFS2dBm>8.59</dBFS2dBm>
				</Point>
				<Point>
					<RFDSA>24.0</RFDSA>
					<dBFS2dBm>9.59</dBFS2dBm>
				</Point>
				<Point>
					<RFDSA>25.0</RFDSA>
					<dBFS2dBm>10.59</dBFS2dBm>
				</Point>
				<Point>
					<RFDSA>26.0</RFDSA>
					<dBFS2dBm>11.59</dBFS2dBm>
				</Point>
				<Point>
					<RFDSA>27.0</RFDSA>
					<dBFS2dBm>12.59</dBFS2dBm>
				</Point>
				<Point>
					<RFDSA>28.0</RFDSA>
					<dBFS2dBm>13.59</dBFS2dBm>
				</Point>
				<Point>
					<RFDSA>29.0</RFDSA>
					<dBFS2dBm>14.59</dBFS2dBm>
				</Point>
				<Point>
					<RFDSA>30.0</RFDSA>
					<dBFS2dBm>15.59</dBFS2dBm>
				</Point>
				<Point>
					<RFDSA>31.0</RFDSA>
					<dBFS2dBm>16.59</dBFS2dBm>
				</Point>
			</FrequencyTable>
		</FrequencyBand>
	</RxOpenLoop>
	<RxOpenLoop comment="Calibration for Signal Analysis">
		<!-- The individual Path calibrations are here so as to support different 
			methods, temperature compensations etc. -->
		<Path>2</Path>
		<Date>10/01/2008 15:12:33</Date>
		<LinearTemperatureCompensation>
			<!-- support for multiple methods i.e. linear, ploy, LUT. These are normally 
				fixed at design time against hardware revision from engineers logbook -->
			<Coefficient units="dB/DegC">0.05</Coefficient>
		</LinearTemperatureCompensation>
		<FrequencyBand
			comment="A frequency band represents a small section of the spectrum i.e. a cellular band which share a common IFDSA cal Point
				Frequencies are in kHz, IF and RF DSAs are in dB.">
			<Upper>2400000</Upper>
			<Lower>2300000</Lower>
			<IFDSA>5.5</IFDSA>
			<FrequencyTable>
				<Frequency>2325000</Frequency>
				<Temperature>23.5</Temperature>
				<Point>
					<RFDSA>0.0</RFDSA>
					<dBFS2dBm>-15.19</dBFS2dBm>
				</Point>
				<Point>
					<RFDSA>1.0</RFDSA>
					<dBFS2dBm>-14.19</dBFS2dBm>
				</Point>
				<Point>
					<RFDSA>2.0</RFDSA>
					<dBFS2dBm>-13.19</dBFS2dBm>
				</Point>
				<Point>
					<RFDSA>3.0</RFDSA>
					<dBFS2dBm>-12.19</dBFS2dBm>
				</Point>
				<Point>
					<RFDSA>4.0</RFDSA>
					<dBFS2dBm>-11.19</dBFS2dBm>
				</Point>
				<Point>
					<RFDSA>5.0</RFDSA>
					<dBFS2dBm>-10.19</dBFS2dBm>
				</Point>
				<Point>
					<RFDSA>6.0</RFDSA>
					<dBFS2dBm>-9.19</dBFS2dBm>
				</Point>
				<Point>
					<RFDSA>7.0</RFDSA>
					<dBFS2dBm>-8.19</dBFS2dBm>
				</Point>
				<Point>
					<RFDSA>8.0</RFDSA>
					<dBFS2dBm>-7.19</dBFS2dBm>
				</Point>
				<Point>
					<RFDSA>9.0</RFDSA>
					<dBFS2dBm>-6.19</dBFS2dBm>
				</Point>
				<Point>
					<RFDSA>10.0</RFDSA>
					<dBFS2dBm>-5.19</dBFS2dBm>
				</Point>
				<Point>
					<RFDSA>11.0</RFDSA>
					<dBFS2dBm>-4.19</dBFS2dBm>
				</Point>
				<Point>
					<RFDSA>12.0</RFDSA>
					<dBFS2dBm>-3.19</dBFS2dBm>
				</Point>
				<Point>
					<RFDSA>13.0</RFDSA>
					<dBFS2dBm>-2.19</dBFS2dBm>
				</Point>
				<Point>
					<RFDSA>14.0</RFDSA>
					<dBFS2dBm>-1.19</dBFS2dBm>
				</Point>
				<Point>
					<RFDSA>15.0</RFDSA>
					<dBFS2dBm>0.19</dBFS2dBm>
				</Point>
				<Point>
					<RFDSA>16.0</RFDSA>
					<dBFS2dBm>1.19</dBFS2dBm>
				</Point>
				<Point>
					<RFDSA>17.0</RFDSA>
					<dBFS2dBm>2.19</dBFS2dBm>
				</Point>
				<Point>
					<RFDSA>18.0</RFDSA>
					<dBFS2dBm>3.19</dBFS2dBm>
				</Point>
				<Point>
					<RFDSA>19.0</RFDSA>
					<dBFS2dBm>4.19</dBFS2dBm>
				</Point>
				<Point>
					<RFDSA>20.0</RFDSA>
					<dBFS2dBm>5.19</dBFS2dBm>
				</Point>
				<Point>
					<RFDSA>21.0</RFDSA>
					<dBFS2dBm>6.19</dBFS2dBm>
				</Point>
				<Point>
					<RFDSA>22.0</RFDSA>
					<dBFS2dBm>7.19</dBFS2dBm>
				</Point>
				<Point>
					<RFDSA>23.0</RFDSA>
					<dBFS2dBm>8.19</dBFS2dBm>
				</Point>
				<Point>
					<RFDSA>24.0</RFDSA>
					<dBFS2dBm>9.19</dBFS2dBm>
				</Point>
				<Point>
					<RFDSA>25.0</RFDSA>
					<dBFS2dBm>10.19</dBFS2dBm>
				</Point>
				<Point>
					<RFDSA>26.0</RFDSA>
					<dBFS2dBm>11.19</dBFS2dBm>
				</Point>
				<Point>
					<RFDSA>27.0</RFDSA>
					<dBFS2dBm>12.19</dBFS2dBm>
				</Point>
				<Point>
					<RFDSA>28.0</RFDSA>
					<dBFS2dBm>13.19</dBFS2dBm>
				</Point>
				<Point>
					<RFDSA>29.0</RFDSA>
					<dBFS2dBm>14.19</dBFS2dBm>
				</Point>
				<Point>
					<RFDSA>30.0</RFDSA>
					<dBFS2dBm>15.19</dBFS2dBm>
				</Point>
				<Point>
					<RFDSA>31.0</RFDSA>
					<dBFS2dBm>16.19</dBFS2dBm>
				</Point>
			</FrequencyTable>
			<FrequencyTable>
				<Frequency>2335000</Frequency>
				<Temperature>23.5</Temperature>
				<Point>
					<RFDSA>0.0</RFDSA>
					<dBFS2dBm>-12.29</dBFS2dBm>
				</Point>
				<Point>
					<RFDSA>1.0</RFDSA>
					<dBFS2dBm>-12.29</dBFS2dBm>
				</Point>
				<Point>
					<RFDSA>2.0</RFDSA>
					<dBFS2dBm>-12.29</dBFS2dBm>
				</Point>
				<Point>
					<RFDSA>3.0</RFDSA>
					<dBFS2dBm>-12.29</dBFS2dBm>
				</Point>
				<Point>
					<RFDSA>4.0</RFDSA>
					<dBFS2dBm>-11.29</dBFS2dBm>
				</Point>
				<Point>
					<RFDSA>5.0</RFDSA>
					<dBFS2dBm>-10.29</dBFS2dBm>
				</Point>
				<Point>
					<RFDSA>6.0</RFDSA>
					<dBFS2dBm>-9.29</dBFS2dBm>
				</Point>
				<Point>
					<RFDSA>7.0</RFDSA>
					<dBFS2dBm>-8.29</dBFS2dBm>
				</Point>
				<Point>
					<RFDSA>8.0</RFDSA>
					<dBFS2dBm>-7.29</dBFS2dBm>
				</Point>
				<Point>
					<RFDSA>9.0</RFDSA>
					<dBFS2dBm>-6.29</dBFS2dBm>
				</Point>
				<Point>
					<RFDSA>10.0</RFDSA>
					<dBFS2dBm>-5.29</dBFS2dBm>
				</Point>
				<Point>
					<RFDSA>11.0</RFDSA>
					<dBFS2dBm>-4.29</dBFS2dBm>
				</Point>
				<Point>
					<RFDSA>12.0</RFDSA>
					<dBFS2dBm>-3.29</dBFS2dBm>
				</Point>
				<Point>
					<RFDSA>13.0</RFDSA>
					<dBFS2dBm>-2.29</dBFS2dBm>
				</Point>
				<Point>
					<RFDSA>14.0</RFDSA>
					<dBFS2dBm>-1.29</dBFS2dBm>
				</Point>
				<Point>
					<RFDSA>15.0</RFDSA>
					<dBFS2dBm>0.29</dBFS2dBm>
				</Point>
				<Point>
					<RFDSA>16.0</RFDSA>
					<dBFS2dBm>1.29</dBFS2dBm>
				</Point>
				<Point>
					<RFDSA>17.0</RFDSA>
					<dBFS2dBm>2.29</dBFS2dBm>
				</Point>
				<Point>
					<RFDSA>18.0</RFDSA>
					<dBFS2dBm>3.29</dBFS2dBm>
				</Point>
				<Point>
					<RFDSA>19.0</RFDSA>
					<dBFS2dBm>4.29</dBFS2dBm>
				</Point>
				<Point>
					<RFDSA>20.0</RFDSA>
					<dBFS2dBm>5.29</dBFS2dBm>
				</Point>
				<Point>
					<RFDSA>21.0</RFDSA>
					<dBFS2dBm>6.29</dBFS2dBm>
				</Point>
				<Point>
					<RFDSA>22.0</RFDSA>
					<dBFS2dBm>7.29</dBFS2dBm>
				</Point>
				<Point>
					<RFDSA>23.0</RFDSA>
					<dBFS2dBm>8.29</dBFS2dBm>
				</Point>
				<Point>
					<RFDSA>24.0</RFDSA>
					<dBFS2dBm>9.29</dBFS2dBm>
				</Point>
				<Point>
					<RFDSA>25.0</RFDSA>
					<dBFS2dBm>10.29</dBFS2dBm>
				</Point>
				<Point>
					<RFDSA>26.0</RFDSA>
					<dBFS2dBm>11.29</dBFS2dBm>
				</Point>
				<Point>
					<RFDSA>27.0</RFDSA>
					<dBFS2dBm>12.29</dBFS2dBm>
				</Point>
				<Point>
					<RFDSA>28.0</RFDSA>
					<dBFS2dBm>13.29</dBFS2dBm>
				</Point>
				<Point>
					<RFDSA>29.0</RFDSA>
					<dBFS2dBm>14.29</dBFS2dBm>
				</Point>
				<Point>
					<RFDSA>30.0</RFDSA>
					<dBFS2dBm>15.29</dBFS2dBm>
				</Point>
				<Point>
					<RFDSA>31.0</RFDSA>
					<dBFS2dBm>16.29</dBFS2dBm>
				</Point>
			</FrequencyTable>
			<FrequencyTable>
				<Frequency>2345000</Frequency>
				<Temperature>23.5</Temperature>
				<Point>
					<RFDSA>0.0</RFDSA>
					<dBFS2dBm>-12.39</dBFS2dBm>
				</Point>
				<Point>
					<RFDSA>1.0</RFDSA>
					<dBFS2dBm>-12.39</dBFS2dBm>
				</Point>
				<Point>
					<RFDSA>2.0</RFDSA>
					<dBFS2dBm>-12.39</dBFS2dBm>
				</Point>
				<Point>
					<RFDSA>3.0</RFDSA>
					<dBFS2dBm>-12.39</dBFS2dBm>
				</Point>
				<Point>
					<RFDSA>4.0</RFDSA>
					<dBFS2dBm>-11.39</dBFS2dBm>
				</Point>
				<Point>
					<RFDSA>5.0</RFDSA>
					<dBFS2dBm>-10.39</dBFS2dBm>
				</Point>
				<Point>
					<RFDSA>6.0</RFDSA>
					<dBFS2dBm>-9.39</dBFS2dBm>
				</Point>
				<Point>
					<RFDSA>7.0</RFDSA>
					<dBFS2dBm>-8.39</dBFS2dBm>
				</Point>
				<Point>
					<RFDSA>8.0</RFDSA>
					<dBFS2dBm>-7.39</dBFS2dBm>
				</Point>
				<Point>
					<RFDSA>9.0</RFDSA>
					<dBFS2dBm>-6.39</dBFS2dBm>
				</Point>
				<Point>
					<RFDSA>10.0</RFDSA>
					<dBFS2dBm>-5.39</dBFS2dBm>
				</Point>
				<Point>
					<RFDSA>11.0</RFDSA>
					<dBFS2dBm>-4.39</dBFS2dBm>
				</Point>
				<Point>
					<RFDSA>12.0</RFDSA>
					<dBFS2dBm>-3.39</dBFS2dBm>
				</Point>
				<Point>
					<RFDSA>13.0</RFDSA>
					<dBFS2dBm>-2.39</dBFS2dBm>
				</Point>
				<Point>
					<RFDSA>14.0</RFDSA>
					<dBFS2dBm>-1.39</dBFS2dBm>
				</Point>
				<Point>
					<RFDSA>15.0</RFDSA>
					<dBFS2dBm>0.39</dBFS2dBm>
				</Point>
				<Point>
					<RFDSA>16.0</RFDSA>
					<dBFS2dBm>1.39</dBFS2dBm>
				</Point>
				<Point>
					<RFDSA>17.0</RFDSA>
					<dBFS2dBm>2.39</dBFS2dBm>
				</Point>
				<Point>
					<RFDSA>18.0</RFDSA>
					<dBFS2dBm>3.39</dBFS2dBm>
				</Point>
				<Point>
					<RFDSA>19.0</RFDSA>
					<dBFS2dBm>4.39</dBFS2dBm>
				</Point>
				<Point>
					<RFDSA>20.0</RFDSA>
					<dBFS2dBm>5.39</dBFS2dBm>
				</Point>
				<Point>
					<RFDSA>21.0</RFDSA>
					<dBFS2dBm>6.39</dBFS2dBm>
				</Point>
				<Point>
					<RFDSA>22.0</RFDSA>
					<dBFS2dBm>7.39</dBFS2dBm>
				</Point>
				<Point>
					<RFDSA>23.0</RFDSA>
					<dBFS2dBm>8.39</dBFS2dBm>
				</Point>
				<Point>
					<RFDSA>24.0</RFDSA>
					<dBFS2dBm>9.39</dBFS2dBm>
				</Point>
				<Point>
					<RFDSA>25.0</RFDSA>
					<dBFS2dBm>10.39</dBFS2dBm>
				</Point>
				<Point>
					<RFDSA>26.0</RFDSA>
					<dBFS2dBm>11.39</dBFS2dBm>
				</Point>
				<Point>
					<RFDSA>27.0</RFDSA>
					<dBFS2dBm>12.39</dBFS2dBm>
				</Point>
				<Point>
					<RFDSA>28.0</RFDSA>
					<dBFS2dBm>13.39</dBFS2dBm>
				</Point>
				<Point>
					<RFDSA>29.0</RFDSA>
					<dBFS2dBm>14.39</dBFS2dBm>
				</Point>
				<Point>
					<RFDSA>30.0</RFDSA>
					<dBFS2dBm>15.39</dBFS2dBm>
				</Point>
				<Point>
					<RFDSA>31.0</RFDSA>
					<dBFS2dBm>16.39</dBFS2dBm>
				</Point>
			</FrequencyTable>
			<FrequencyTable>
				<Frequency>2355000</Frequency>
				<Temperature>23.5</Temperature>
				<Point>
					<RFDSA>0.0</RFDSA>
					<dBFS2dBm>-12.49</dBFS2dBm>
				</Point>
				<Point>
					<RFDSA>1.0</RFDSA>
					<dBFS2dBm>-12.49</dBFS2dBm>
				</Point>
				<Point>
					<RFDSA>2.0</RFDSA>
					<dBFS2dBm>-12.49</dBFS2dBm>
				</Point>
				<Point>
					<RFDSA>3.0</RFDSA>
					<dBFS2dBm>-12.49</dBFS2dBm>
				</Point>
				<Point>
					<RFDSA>4.0</RFDSA>
					<dBFS2dBm>-11.49</dBFS2dBm>
				</Point>
				<Point>
					<RFDSA>5.0</RFDSA>
					<dBFS2dBm>-10.49</dBFS2dBm>
				</Point>
				<Point>
					<RFDSA>6.0</RFDSA>
					<dBFS2dBm>-9.49</dBFS2dBm>
				</Point>
				<Point>
					<RFDSA>7.0</RFDSA>
					<dBFS2dBm>-8.49</dBFS2dBm>
				</Point>
				<Point>
					<RFDSA>8.0</RFDSA>
					<dBFS2dBm>-7.49</dBFS2dBm>
				</Point>
				<Point>
					<RFDSA>9.0</RFDSA>
					<dBFS2dBm>-6.49</dBFS2dBm>
				</Point>
				<Point>
					<RFDSA>10.0</RFDSA>
					<dBFS2dBm>-5.49</dBFS2dBm>
				</Point>
				<Point>
					<RFDSA>11.0</RFDSA>
					<dBFS2dBm>-4.49</dBFS2dBm>
				</Point>
				<Point>
					<RFDSA>12.0</RFDSA>
					<dBFS2dBm>-3.49</dBFS2dBm>
				</Point>
				<Point>
					<RFDSA>13.0</RFDSA>
					<dBFS2dBm>-2.49</dBFS2dBm>
				</Point>
				<Point>
					<RFDSA>14.0</RFDSA>
					<dBFS2dBm>-1.49</dBFS2dBm>
				</Point>
				<Point>
					<RFDSA>15.0</RFDSA>
					<dBFS2dBm>0.49</dBFS2dBm>
				</Point>
				<Point>
					<RFDSA>16.0</RFDSA>
					<dBFS2dBm>1.49</dBFS2dBm>
				</Point>
				<Point>
					<RFDSA>17.0</RFDSA>
					<dBFS2dBm>2.49</dBFS2dBm>
				</Point>
				<Point>
					<RFDSA>18.0</RFDSA>
					<dBFS2dBm>3.49</dBFS2dBm>
				</Point>
				<Point>
					<RFDSA>19.0</RFDSA>
					<dBFS2dBm>4.49</dBFS2dBm>
				</Point>
				<Point>
					<RFDSA>20.0</RFDSA>
					<dBFS2dBm>5.49</dBFS2dBm>
				</Point>
				<Point>
					<RFDSA>21.0</RFDSA>
					<dBFS2dBm>6.49</dBFS2dBm>
				</Point>
				<Point>
					<RFDSA>22.0</RFDSA>
					<dBFS2dBm>7.49</dBFS2dBm>
				</Point>
				<Point>
					<RFDSA>23.0</RFDSA>
					<dBFS2dBm>8.49</dBFS2dBm>
				</Point>
				<Point>
					<RFDSA>24.0</RFDSA>
					<dBFS2dBm>9.49</dBFS2dBm>
				</Point>
				<Point>
					<RFDSA>25.0</RFDSA>
					<dBFS2dBm>10.49</dBFS2dBm>
				</Point>
				<Point>
					<RFDSA>26.0</RFDSA>
					<dBFS2dBm>11.49</dBFS2dBm>
				</Point>
				<Point>
					<RFDSA>27.0</RFDSA>
					<dBFS2dBm>12.49</dBFS2dBm>
				</Point>
				<Point>
					<RFDSA>28.0</RFDSA>
					<dBFS2dBm>13.49</dBFS2dBm>
				</Point>
				<Point>
					<RFDSA>29.0</RFDSA>
					<dBFS2dBm>14.49</dBFS2dBm>
				</Point>
				<Point>
					<RFDSA>30.0</RFDSA>
					<dBFS2dBm>15.49</dBFS2dBm>
				</Point>
				<Point>
					<RFDSA>31.0</RFDSA>
					<dBFS2dBm>16.49</dBFS2dBm>
				</Point>
			</FrequencyTable>
			<FrequencyTable>
				<Frequency>2365000</Frequency>
				<Temperature>23.5</Temperature>
				<Point>
					<RFDSA>0.0</RFDSA>
					<dBFS2dBm>-12.59</dBFS2dBm>
				</Point>
				<Point>
					<RFDSA>1.0</RFDSA>
					<dBFS2dBm>-12.59</dBFS2dBm>
				</Point>
				<Point>
					<RFDSA>2.0</RFDSA>
					<dBFS2dBm>-12.59</dBFS2dBm>
				</Point>
				<Point>
					<RFDSA>3.0</RFDSA>
					<dBFS2dBm>-12.59</dBFS2dBm>
				</Point>
				<Point>
					<RFDSA>4.0</RFDSA>
					<dBFS2dBm>-11.59</dBFS2dBm>
				</Point>
				<Point>
					<RFDSA>5.0</RFDSA>
					<dBFS2dBm>-10.59</dBFS2dBm>
				</Point>
				<Point>
					<RFDSA>6.0</RFDSA>
					<dBFS2dBm>-9.59</dBFS2dBm>
				</Point>
				<Point>
					<RFDSA>7.0</RFDSA>
					<dBFS2dBm>-8.59</dBFS2dBm>
				</Point>
				<Point>
					<RFDSA>8.0</RFDSA>
					<dBFS2dBm>-7.59</dBFS2dBm>
				</Point>
				<Point>
					<RFDSA>9.0</RFDSA>
					<dBFS2dBm>-6.59</dBFS2dBm>
				</Point>
				<Point>
					<RFDSA>10.0</RFDSA>
					<dBFS2dBm>-5.59</dBFS2dBm>
				</Point>
				<Point>
					<RFDSA>11.0</RFDSA>
					<dBFS2dBm>-4.59</dBFS2dBm>
				</Point>
				<Point>
					<RFDSA>12.0</RFDSA>
					<dBFS2dBm>-3.59</dBFS2dBm>
				</Point>
				<Point>
					<RFDSA>13.0</RFDSA>
					<dBFS2dBm>-2.59</dBFS2dBm>
				</Point>
				<Point>
					<RFDSA>14.0</RFDSA>
					<dBFS2dBm>-1.59</dBFS2dBm>
				</Point>
				<Point>
					<RFDSA>15.0</RFDSA>
					<dBFS2dBm>0.59</dBFS2dBm>
				</Point>
				<Point>
					<RFDSA>16.0</RFDSA>
					<dBFS2dBm>1.59</dBFS2dBm>
				</Point>
				<Point>
					<RFDSA>17.0</RFDSA>
					<dBFS2dBm>2.59</dBFS2dBm>
				</Point>
				<Point>
					<RFDSA>18.0</RFDSA>
					<dBFS2dBm>3.59</dBFS2dBm>
				</Point>
				<Point>
					<RFDSA>19.0</RFDSA>
					<dBFS2dBm>4.59</dBFS2dBm>
				</Point>
				<Point>
					<RFDSA>20.0</RFDSA>
					<dBFS2dBm>5.59</dBFS2dBm>
				</Point>
				<Point>
					<RFDSA>21.0</RFDSA>
					<dBFS2dBm>6.59</dBFS2dBm>
				</Point>
				<Point>
					<RFDSA>22.0</RFDSA>
					<dBFS2dBm>7.59</dBFS2dBm>
				</Point>
				<Point>
					<RFDSA>23.0</RFDSA>
					<dBFS2dBm>8.59</dBFS2dBm>
				</Point>
				<Point>
					<RFDSA>24.0</RFDSA>
					<dBFS2dBm>9.59</dBFS2dBm>
				</Point>
				<Point>
					<RFDSA>25.0</RFDSA>
					<dBFS2dBm>10.59</dBFS2dBm>
				</Point>
				<Point>
					<RFDSA>26.0</RFDSA>
					<dBFS2dBm>11.59</dBFS2dBm>
				</Point>
				<Point>
					<RFDSA>27.0</RFDSA>
					<dBFS2dBm>12.59</dBFS2dBm>
				</Point>
				<Point>
					<RFDSA>28.0</RFDSA>
					<dBFS2dBm>13.59</dBFS2dBm>
				</Point>
				<Point>
					<RFDSA>29.0</RFDSA>
					<dBFS2dBm>14.59</dBFS2dBm>
				</Point>
				<Point>
					<RFDSA>30.0</RFDSA>
					<dBFS2dBm>15.59</dBFS2dBm>
				</Point>
				<Point>
					<RFDSA></RFDSA>
					<dBFS2dBm></dBFS2dBm>
				</Point>
			</FrequencyTable>
		</FrequencyBand>
	</RxOpenLoop>
</FTUCalibrationRx>
  